zdppy_requests/__init__.py
zdppy_requests/_internal_utils.py
zdppy_requests/adapters.py
zdppy_requests/api.py
zdppy_requests/auth.py
zdppy_requests/certifi/__init__.py
zdppy_requests/certifi/__main__.py
zdppy_requests/certifi/cacert.pem
zdppy_requests/certifi/core.py
zdppy_requests/certs.py
zdppy_requests/charset_normalizer/__init__.py
zdppy_requests/charset_normalizer/api.py
zdppy_requests/charset_normalizer/assets/__init__.py
zdppy_requests/charset_normalizer/cd.py
zdppy_requests/charset_normalizer/cli/__init__.py
zdppy_requests/charset_normalizer/cli/normalizer.py
zdppy_requests/charset_normalizer/constant.py
zdppy_requests/charset_normalizer/legacy.py
zdppy_requests/charset_normalizer/md.py
zdppy_requests/charset_normalizer/models.py
zdppy_requests/charset_normalizer/py.typed
zdppy_requests/charset_normalizer/utils.py
zdppy_requests/charset_normalizer/version.py
zdppy_requests/compat.py
zdppy_requests/cookie.py
zdppy_requests/cookies.py
zdppy_requests/exceptions.py
zdppy_requests/help.py
zdppy_requests/hooks.py
zdppy_requests/idna/__init__.py
zdppy_requests/idna/codec.py
zdppy_requests/idna/compat.py
zdppy_requests/idna/core.py
zdppy_requests/idna/idnadata.py
zdppy_requests/idna/intranges.py
zdppy_requests/idna/package_data.py
zdppy_requests/idna/py.typed
zdppy_requests/idna/uts46data.py
zdppy_requests/models.py
zdppy_requests/packages.py
zdppy_requests/sessions.py
zdppy_requests/status_codes.py
zdppy_requests/structures.py
zdppy_requests/urllib3/__init__.py
zdppy_requests/urllib3/_collections.py
zdppy_requests/urllib3/_version.py
zdppy_requests/urllib3/connection.py
zdppy_requests/urllib3/connectionpool.py
zdppy_requests/urllib3/contrib/__init__.py
zdppy_requests/urllib3/contrib/_appengine_environ.py
zdppy_requests/urllib3/contrib/_securetransport/__init__.py
zdppy_requests/urllib3/contrib/_securetransport/bindings.py
zdppy_requests/urllib3/contrib/_securetransport/low_level.py
zdppy_requests/urllib3/contrib/appengine.py
zdppy_requests-0.1.3.dist-info/METADATA
zdppy_requests-0.1.3.dist-info/LICENSE
zdppy_requests-0.1.3.dist-info/WHEEL
zdppy_requests-0.1.3.dist-info/RECORD
