Metadata-Version: 2.1
Name: zdppy-requests
Version: 0.1.3
Summary: 
Author: zhangdapeng520
Author-email: 1156956636@qq.com
Requires-Python: >=3.9,<4.0
Classifier: Programming Language :: Python :: 3
Classifier: Programming Language :: Python :: 3.9
Classifier: Programming Language :: Python :: 3.10
Classifier: Programming Language :: Python :: 3.11
